LICENSE
README.md
setup.py
amazon_ad/__init__.py
amazon_ad/api/__init__.py
amazon_ad/api/auth.py
amazon_ad/api/base.py
amazon_ad/api/profiles.py
amazon_ad/api/report.py
amazon_ad/api/amazon_attribution/__init__.py
amazon_ad/api/amazon_attribution/advertisers.py
amazon_ad/api/amazon_attribution/publishers.py
amazon_ad/api/amazon_attribution/reports.py
amazon_ad/api/dsp/__init__.py
amazon_ad/api/dsp/report.py
amazon_ad/api/sb/__init__.py
amazon_ad/api/sb/campaigns.py
amazon_ad/api/sb/report.py
amazon_ad/api/sd/__init__.py
amazon_ad/api/sd/report.py
amazon_ad/api/sd/scripts.py
amazon_ad/api/sp/__init__.py
amazon_ad/api/sp/report.py
amazon_ad/api_v3/__init__.py
amazon_ad/api_v3/adapters.py
amazon_ad/api_v3/base.py
amazon_ad/api_v3/report.py
amazon_ad/api_v3/billing/__init__.py
amazon_ad/api_v3/billing/report.py
amazon_ad/api_v3/sb/__init__.py
amazon_ad/api_v3/sb/report.py
amazon_ad/api_v3/sd/__init__.py
amazon_ad/api_v3/sd/report.py
amazon_ad/api_v3/sp/__init__.py
amazon_ad/api_v3/sp/report.py
amazon_ad/client/__init__.py
amazon_ad/client/auth.py
amazon_ad/client/base.py
amazon_ad/client/service.py
amazon_ad/core/__init__.py
amazon_ad/core/consts.py
amazon_ad/core/exceptions.py
amazon_ad/core/utils/__init__.py
amazon_ad/core/utils/amazon.py
amazon_ad/core/utils/serialize.py
amazon_ad/core/utils/text.py
amazon_ad_sdk.egg-info/PKG-INFO
amazon_ad_sdk.egg-info/SOURCES.txt
amazon_ad_sdk.egg-info/dependency_links.txt
amazon_ad_sdk.egg-info/requires.txt
amazon_ad_sdk.egg-info/top_level.txt