Metadata-Version: 2.1
Name: amazon-ad-sdk
Version: 0.2.17
Summary: Amazon Advertising SDK
Home-page: UNKNOWN
Author: Ryan
Author-email: 931798845@qq.com
License: UNKNOWN
Platform: UNKNOWN
Requires-Python: >=3.6
License-File: LICENSE
